pytv/Converter.py
pytv/ModuleLoader.py
pytv/__init__.py
pytv/utils.py
voldelog-0.3.dist-info/LICENSE
voldelog-0.3.dist-info/METADATA
voldelog-0.3.dist-info/WHEEL
voldelog-0.3.dist-info/top_level.txt
voldelog-0.3.dist-info/RECORD
